fantailp_package/__init__.py
fantailp_package/script.py
fantailp_package-0.1.dist-info/METADATA
fantailp_package-0.1.dist-info/WHEEL
fantailp_package-0.1.dist-info/entry_points.txt
fantailp_package-0.1.dist-info/top_level.txt
fantailp_package-0.1.dist-info/RECORD
