Metadata-Version: 2.1
Name: fantailp-package
Version: 0.1
Summary: A brief description of your package
Home-page: UNKNOWN
Author: Your Name
Author-email: your.email@example.com
License: UNKNOWN
Platform: UNKNOWN
